{
    "rows": [
{
            "RNUM": "66",
            "ID": "1",
            "NAME": "Account"
        },        {
            "RNUM": "97",
            "ID": "2",
            "NAME": "Account"
        },        {
            "RNUM": "45",
            "ID": "3",
            "NAME": "Account"
        },        {
            "RNUM": "34",
            "ID": "4",
            "NAME": "Account"
        },        {
            "RNUM": "28",
            "ID": "5",
            "NAME": "Account"
        },        {
            "RNUM": "38",
            "ID": "6",
            "NAME": "Account"
        },        {
            "RNUM": "1",
            "ID": "7",
            "NAME": "Account"
        },        {
            "RNUM": "79",
            "ID": "8",
            "NAME": "Account"
        },        {
            "RNUM": "73",
            "ID": "9",
            "NAME": "Account"
        },        {
            "RNUM": "76",
            "ID": "10",
            "NAME": "Account"
        },        {
            "RNUM": "61",
            "ID": "11",
            "NAME": "Account"
        },        {
            "RNUM": "59",
            "ID": "12",
            "NAME": "Account"
        },        {
            "RNUM": "6",
            "ID": "13",
            "NAME": "Account"
        },        {
            "RNUM": "52",
            "ID": "14",
            "NAME": "Account"
        },        {
            "RNUM": "19",
            "ID": "15",
            "NAME": "Account"
        },        {
            "RNUM": "43",
            "ID": "16",
            "NAME": "Account"
        },        {
            "RNUM": "56",
            "ID": "17",
            "NAME": "Account"
        },        {
            "RNUM": "19",
            "ID": "18",
            "NAME": "Account"
        },        {
            "RNUM": "23",
            "ID": "19",
            "NAME": "Account"
        },        {
            "RNUM": "66",
            "ID": "20",
            "NAME": "Account"
        },        {
            "RNUM": "56",
            "ID": "21",
            "NAME": "Account"
        },        {
            "RNUM": "77",
            "ID": "22",
            "NAME": "Account"
        },        {
            "RNUM": "13",
            "ID": "23",
            "NAME": "Account"
        },        {
            "RNUM": "3",
            "ID": "24",
            "NAME": "Account"
        },        {
            "RNUM": "81",
            "ID": "25",
            "NAME": "Account"
        }    ],
    "paginatedRowCount": 25,
    "totalRowCount": 50
}